README.md
setup.py
comsyl/__init__.py
comsyl/calculateAutocorrelation.py
comsyl.egg-info/PKG-INFO
comsyl.egg-info/SOURCES.txt
comsyl.egg-info/dependency_links.txt
comsyl.egg-info/requires.txt
comsyl.egg-info/top_level.txt
comsyl/autocorrelation/AutocorrelationBuilder.py
comsyl/autocorrelation/AutocorrelationBuilderStrategies.py
comsyl/autocorrelation/AutocorrelationBuilderStrategy.py
comsyl/autocorrelation/AutocorrelationFunction.py
comsyl/autocorrelation/AutocorrelationFunctionIO.py
comsyl/autocorrelation/AutocorrelationFunctionPropagator.py
comsyl/autocorrelation/AutocorrelationInfo.py
comsyl/autocorrelation/AutocorrelationOperator.py
comsyl/autocorrelation/AutocorrelationSimulator.py
comsyl/autocorrelation/AutocorrelationSimulatorConfiguration.py
comsyl/autocorrelation/CompactAFReader.py
comsyl/autocorrelation/DegreeOfCoherence.py
comsyl/autocorrelation/DivergenceAction.py
comsyl/autocorrelation/PhaseSpaceDensity.py
comsyl/autocorrelation/SigmaMatrix.py
comsyl/autocorrelation/__init__.py
comsyl/infos/Lattices.py
comsyl/infos/Undulators.py
comsyl/infos/__init__.py
comsyl/mathcomsyl/Convolution.py
comsyl/mathcomsyl/Eigenmoder.py
comsyl/mathcomsyl/EigenmoderSeparation.py
comsyl/mathcomsyl/EigenmoderStrategy.py
comsyl/mathcomsyl/Eigensolver.py
comsyl/mathcomsyl/FourierTransform.py
comsyl/mathcomsyl/GaussianSchellModel.py
comsyl/mathcomsyl/Interpolation.py
comsyl/mathcomsyl/MatrixBuilder.py
comsyl/mathcomsyl/Twoform.py
comsyl/mathcomsyl/TwoformVectors.py
comsyl/mathcomsyl/__init__.py
comsyl/mathcomsyl/utils.py
comsyl/parallel/DistributionPlan.py
comsyl/parallel/DistributionPlanPETSc.py
comsyl/parallel/ParallelEigensolver.py
comsyl/parallel/ParallelLinearOperator.py
comsyl/parallel/ParallelMatrix.py
comsyl/parallel/ParallelMatrixPETSc.py
comsyl/parallel/ParallelVector.py
comsyl/parallel/TwoformPETSc.py
comsyl/parallel/__init__.py
comsyl/parallel/tools.py
comsyl/parallel/utils.py
comsyl/utils/Logger.py
comsyl/utils/Magneticfield.py
comsyl/utils/Trajectory.py
comsyl/utils/__init__.py
comsyl/waveoptics/ComsylWofryBeamline.py
comsyl/waveoptics/ComsylWofryBeamlineElement.py
comsyl/waveoptics/GaussianWavefrontBuilder.py
