Metadata-Version: 1.0
Name: comsyl
Version: 1.0.12
Summary: Coherent modes for synchrotron light
Home-page: https://github.com/mark-glass/comsyl/
Author: Mark Glass
Author-email: mark.glass@esrf.fr
License: UNKNOWN
Platform: UNKNOWN
